mesa_interactive/__about__.py
mesa_interactive/__init__.py
mesa_interactive/interactive.py
mesa_interactive/timeline_controls.py
mesa_interactive/user_inputs.py
mesa_interactive/util.py
mesa_interactive/components/__init__.py
mesa_interactive/components/charts.py
mesa_interactive/components/grid.py
mesa_interactive/components/markdown.py
mesa_interactive-0.0.5.dist-info/METADATA
mesa_interactive-0.0.5.dist-info/WHEEL
mesa_interactive-0.0.5.dist-info/licenses/LICENSE
mesa_interactive-0.0.5.dist-info/RECORD
