Metadata-Version: 2.1
Name: mesa_interactive
Version: 0.0.5
Summary: Interactive visualization of Mesa simulations
License-Expression: MIT
License-File: LICENSE
Requires-Python: >=3.6
Requires-Dist: altair
Requires-Dist: mesa
Requires-Dist: solara
